baseweb_plugin_oauth_protectedpage/__init__.py
baseweb_plugin_oauth_protectedpage/auth.js
baseweb_plugin_oauth_protectedpage/auth.py
baseweb_plugin_oauth_protectedpage/protectedpage.js
docs/__init__.py
docs/conf.py
example/__init__.py
example/app.py
example/fake_mongo.py
baseweb_plugin_oauth_protectedpage-0.0.1.dist-info/LICENSE.txt
baseweb_plugin_oauth_protectedpage-0.0.1.dist-info/METADATA
baseweb_plugin_oauth_protectedpage-0.0.1.dist-info/WHEEL
baseweb_plugin_oauth_protectedpage-0.0.1.dist-info/top_level.txt
baseweb_plugin_oauth_protectedpage-0.0.1.dist-info/RECORD
