Metadata-Version: 2.1
Name: baseweb-plugin-oauth-protectedpage
Version: 0.0.1
Summary: baseweb plugin providing an oauth protected page component
Home-page: https://github.com/christophevg/baseweb-plugin-oauth-protectedpage
Author: Christophe VG
License: MIT
Keywords: baseweb plugin oauth protected page component
Platform: UNKNOWN
Classifier: Intended Audience :: Developers
Classifier: Programming Language :: Python
Classifier: Development Status :: 4 - Beta
Classifier: Programming Language :: Python :: 3.8
Classifier: Programming Language :: Python :: 3.9
Classifier: Programming Language :: Python :: 3.10
Classifier: Programming Language :: Python :: 3.11
Classifier: License :: OSI Approved :: MIT License
Classifier: Environment :: Plugins
Classifier: Environment :: Web Environment
Requires-Dist: baseweb
Requires-Dist: oatk
Requires-Dist: flask-login
